astools/__init__.py
astools/mc.py
astools/myfunclib.py
astools/processim.py
astools/sinout.py
astools/splot.py
astools-0.1.dist-info/LICENSE
astools-0.1.dist-info/METADATA
astools-0.1.dist-info/WHEEL
astools-0.1.dist-info/entry_points.txt
astools-0.1.dist-info/top_level.txt
astools-0.1.dist-info/RECORD
