Metadata-Version: 2.1
Name: astools
Version: 0.1
Summary: Python tool kit for astro uses.
Home-page: https://github.com/kxxdhdn/Silo
Author: D. HU
Author-email: dangning.hu@cea.fr
License: BSD
Keywords: astronomy astrophysics
Platform: UNKNOWN
Classifier: Programming Language :: Python :: 3
Classifier: License :: OSI Approved :: BSD License
Classifier: Operating System :: MacOS
Requires-Python: >=3.6
Requires-Dist: h5py
Requires-Dist: reproject
